fixer_app_ihungo/__init__.py
fixer_app_ihungo/broker_request.py
fixer_app_ihungo-0.0.2.dist-info/LICENSE
fixer_app_ihungo-0.0.2.dist-info/METADATA
fixer_app_ihungo-0.0.2.dist-info/WHEEL
fixer_app_ihungo-0.0.2.dist-info/top_level.txt
fixer_app_ihungo-0.0.2.dist-info/RECORD
