Metadata-Version: 2.1
Name: fixer-app-ihungo
Version: 0.0.2
Summary: My first Python package
Author: Fixer
Author-email: eromero@ihungo.com
License: MIT License
Keywords: python,first package
Classifier: Development Status :: 3 - Alpha
Classifier: Intended Audience :: Education
Classifier: Programming Language :: Python :: 2
Classifier: Programming Language :: Python :: 3
Classifier: Operating System :: MacOS :: MacOS X
Classifier: Operating System :: Microsoft :: Windows
License-File: LICENSE
Requires-Dist: requests
